pymetdense/__init__.py
pymetdense/parser.py
pymetdense-1.0.1.dist-info/METADATA
pymetdense-1.0.1.dist-info/WHEEL
pymetdense-1.0.1.dist-info/licenses/LICENSE
pymetdense-1.0.1.dist-info/RECORD
