Metadata-Version: 2.1
Name: pymetdense
Version: 1.0.1
Summary: Parser for .metdense files.
Project-URL: Homepage, https://github.com/anders-biostat/pymetdense
Project-URL: Bug Tracker, https://github.com/anders-biostat/pymetdense/issues
Author-email: Valentin Wüst <valentin.wuest@bioquant.uni-heidelberg.de>
License:                     GNU GENERAL PUBLIC LICENSE
License-File: LICENSE
Classifier: License :: OSI Approved :: GNU General Public License v3 (GPLv3)
Classifier: Operating System :: OS Independent
Classifier: Programming Language :: Python :: 3
Requires-Python: >=3.7
